gpkron/__init__.py
gpkron/gp2d.py
gpkron-0.0.1.dist-info/LICENSE
gpkron-0.0.1.dist-info/METADATA
gpkron-0.0.1.dist-info/WHEEL
gpkron-0.0.1.dist-info/top_level.txt
gpkron-0.0.1.dist-info/RECORD
