Metadata-Version: 2.1
Name: gpkron
Version: 0.0.1
Summary: 2D GP fitting using Kronecker product
Home-page: http://secondearths.sakura.ne.jp/gpkron/
Author: Hajime Kawahara and collaborators
Author-email: divrot@gmail.com
Maintainer: Hajime Kawahara and collaborators
Maintainer-email: divrot@gmail.com
License: MIT
Platform: UNKNOWN
Classifier: Programming Language :: Python
License-File: LICENSE
Requires-Dist: numpy
